bact_math_utils/__init__.py
bact_math_utils/distorted_orbit.py
bact_math_utils/exp_fit.py
bact_math_utils/life_time.py
bact_math_utils/linear_fit.py
bact_math_utils/misc.py
bact_math_utils/stats.py
bact_math_utils/tune.py
bact_math_utils-0.1.0.dist-info/LICENSE
bact_math_utils-0.1.0.dist-info/METADATA
bact_math_utils-0.1.0.dist-info/WHEEL
bact_math_utils-0.1.0.dist-info/RECORD
