Metadata-Version: 2.1
Name: bact-math-utils
Version: 0.1.0
Summary: bact: math and non mathematical utils
Home-page: https://github.com/hz-b/bact-math-utils
License: GPL-3.0
Author: Pierre Schnizer
Requires-Python: >=3.7
Classifier: Development Status :: 4 - Beta
Classifier: Intended Audience :: Science/Research
Classifier: License :: OSI Approved :: GNU General Public License v3 (GPLv3)
Classifier: Programming Language :: Python :: 3
Classifier: Programming Language :: Python :: 3.7
Classifier: Programming Language :: Python :: 3.8
Classifier: Programming Language :: Python :: 3.9
Classifier: Programming Language :: Python :: 3.10
Classifier: Programming Language :: Python :: 3.11
Classifier: Programming Language :: Python :: 3.12
Classifier: Programming Language :: Python :: 3.13
Classifier: Topic :: Scientific/Engineering :: Physics
Requires-Dist: numpy
Requires-Dist: scipy
Project-URL: Documentation, https://github.com/hz-b/bact-math-utils
Project-URL: Repository, https://github.com/hz-b/bact-math-utils
